MANIFEST.in
README.rst
setup.py
docs/HISTORY.txt
docs/INSTALL.txt
docs/LICENSE.GPL
docs/LICENSE.txt
docs/TODO.txt
unice/.DS_Store
unice/__init__.py
unice.portlet.stories.egg-info/PKG-INFO
unice.portlet.stories.egg-info/SOURCES.txt
unice.portlet.stories.egg-info/dependency_links.txt
unice.portlet.stories.egg-info/entry_points.txt
unice.portlet.stories.egg-info/namespace_packages.txt
unice.portlet.stories.egg-info/not-zip-safe
unice.portlet.stories.egg-info/requires.txt
unice.portlet.stories.egg-info/top_level.txt
unice/portlet/.DS_Store
unice/portlet/__init__.py
unice/portlet/stories/.DS_Store
unice/portlet/stories/__init__.py
unice/portlet/stories/configure.zcml
unice/portlet/stories/storiesportlet.pt
unice/portlet/stories/storiesportlet.py
unice/portlet/stories/vocabularies.py
unice/portlet/stories/browser/.DS_Store
unice/portlet/stories/browser/__init__.py
unice/portlet/stories/browser/configure.zcml
unice/portlet/stories/browser/stylesheets/styles.css
unice/portlet/stories/profiles/.DS_Store
unice/portlet/stories/profiles/default/cssregistry.xml
unice/portlet/stories/profiles/default/metadata.xml
unice/portlet/stories/profiles/default/portlets.xml
unice/portlet/stories/tests/__init__.py
unice/portlet/stories/tests/base.py
unice/portlet/stories/tests/test_portlet.py