Metadata-Version: 1.1
Name: unice.portlet.stories
Version: 1.0
Summary: A Plone portlet that shows a stories item.
Home-page: https://github.com/unice/unice.portlet.stories
Author: Universite Nice Sophia Antipolis
Author-email: pi@unice.fr
License: GPL
Keywords: plone portlet
Platform: UNKNOWN
Classifier: Framework :: Plone
Classifier: Programming Language :: Python
Classifier: Topic :: Software Development :: Libraries :: Python Modules
